npm_audit_checkmk/__init__.py
npm_audit_checkmk/__main__.py
npm_audit_checkmk/lib.py
tests/__init__.py
tests/test_lib.py
npm_audit_checkmk-0.1.0.dist-info/LICENSE
npm_audit_checkmk-0.1.0.dist-info/METADATA
npm_audit_checkmk-0.1.0.dist-info/WHEEL
npm_audit_checkmk-0.1.0.dist-info/entry_points.txt
npm_audit_checkmk-0.1.0.dist-info/top_level.txt
npm_audit_checkmk-0.1.0.dist-info/RECORD
